cellmarker_anno/__init__.py
cellmarker_anno-0.0.2.dist-info/METADATA
cellmarker_anno-0.0.2.dist-info/WHEEL
cellmarker_anno-0.0.2.dist-info/top_level.txt
cellmarker_anno-0.0.2.dist-info/RECORD
